[  {
    "bookSourceComment": "",
    "bookSourceGroup": "🎉精品",
    "bookSourceName": "🎉 小说旗①",
    "bookSourceType": 0,
    "bookSourceUrl": "http://www.xs7.cc",
    "bookUrlPattern": "info-",
    "customOrder": -115351,
    "enabled": true,
    "enabledExplore": true,
    "lastUpdateTime": 1606910424449,
    "loginUrl": "",
    "ruleBookInfo": {
      "author": "h1@text##.+作者：\\s*",
      "coverUrl": ".pic img@src",
      "intro": ".intro@html##^\\s*##<br>",
      "kind": "td:contains(分类：)@text&&td:contains(状态：)@text&&td:contains(全文字数：)@text##(分类|状态|全文字数)：|中|已|字",
      "lastChapter": ".book_newchap@tag.a.0@text##^[^第]+\\s+",
      "name": "h1@text##\\s*作者：.+",
      "tocUrl": ".btopt a@href"
    },
    "ruleContent": {
      "content": "id.content@p@textNodes##.*一秒记住.*"
    },
    "ruleExplore": {},
    "ruleSearch": {
      "author": "class.title span@text##作者：",
      "bookList": "id.alist@div[id]:lt(31)",
      "bookUrl": ".title a@href@js:'/info-'+result.match(/\\/(\\d+)\\/?$/)[1]+'.html'",
      "coverUrl": ".pic img@src",
      "lastChapter": "class.sys a@text",
      "name": ".title a@text"
    },
    "ruleToc": {
      "chapterList": ".bookinfo_td a",
      "chapterName": "text",
      "chapterUrl": "href"
    },
    "searchUrl": "http://www.xs7.cc/modules/article/search.php,{\n  \"charset\": \"gb2312\",\n  \"method\": \"POST\",\n  \"body\": \"searchtype=articlename&searchkey={{key}}&action=login\"\n}",
    "weight": 0
  }]