[  {
    "bookSourceComment": "error:Unable to resolve host \"www.630book.cc\": No address associated with hostname\n",
    "bookSourceGroup": "🍺特优,失效",
    "bookSourceName": "🍺 恋上你看书①",
    "bookSourceType": 0,
    "bookSourceUrl": "http://www.630book.cc",
    "bookUrlPattern": "",
    "customOrder": -32782,
    "enabled": true,
    "enabledExplore": true,
    "exploreUrl": "最新入库::http://www.630book.cc/top/postdate/{{page}}.html\n最近更新::http://www.630book.cc/top/lastupdate/{{page}}.html\n玄幻小说::http://www.630book.cc/list/1/{{page}}.html\n仙侠修真::http://www.630book.cc/list/3/{{page}}.html\n历史小说::http://www.630book.cc/list/5/{{page}}.html\n都市小说::http://www.630book.cc/list/4/{{page}}.html\n言情小说::http://www.630book.cc/list/2/{{page}}.html\n科幻小说::http://www.630book.cc/list/8/{{page}}.html\n竞技小说::http://www.630book.cc/list/7/{{page}}.html\n网游小说::http://www.630book.cc/list/6/{{page}}.html\n完本小说::http://www.630book.cc/quanben/{{page}}",
    "lastUpdateTime": 1603336690883,
    "loginUrl": "",
    "ruleBookInfo": {
      "coverUrl": "id.bookdetail@id.picbox@class.img_in@tag.img.0@src",
      "intro": "id.bookdetail@id.info@id.intro@tag.p@textNodes"
    },
    "ruleContent": {
      "content": "id.content@html",
      "replaceRegex": "##一秒记住.*免费读！"
    },
    "ruleExplore": {},
    "ruleSearch": {
      "author": "class.shu_xinxi@tag.h4.0@tag.small.0@text||class.l3@text||class.odd.1@text||id.info@tag.h1.0@text##.*/",
      "bookList": "class.shu_box||id.articlelist@tag.ul.1@tag.li||class.grid@tag.tr!0||id.bookdetail",
      "bookUrl": "class.shu_xinxi@tag.h4.0@tag.a.0@href||class.l2@tag.a.0@href||class.odd.0@tag.a.0@href",
      "coverUrl": "class.shu_img@tag.a.0@tag.img.0@src||id.picbox@class.img_in@tag.img.0@src",
      "lastChapter": "class.l4@text||class.even.0@tag.a.0@text||id.info@class.update@tag.a.0@text",
      "name": "class.shu_xinxi@tag.h4.0@tag.a.0@text||class.l2@tag.a.0@text||class.odd.0@tag.a.0@text||id.info@tag.h1.0@text##/.*"
    },
    "ruleToc": {
      "chapterList": "class.zjlist@tag.dd@tag.a",
      "chapterName": "text",
      "chapterUrl": "href"
    },
    "searchUrl": "http://www.630book.cc/modules/article/search.php?searchtype=articlename&searchkey={{key}}&action=login&submit=搜索,{\n  \"charset\": \"gbk\"\n}",
    "weight": 0
  }]