[  {
    "bookSourceComment": "",
    "bookSourceGroup": "我的书源",
    "bookSourceName": "天翼中文",
    "bookSourceType": 0,
    "bookSourceUrl": "https://book.189dg.com/",
    "customOrder": 0,
    "enabled": false,
    "enabledExplore": false,
    "lastUpdateTime": 0,
    "ruleBookInfo": {
      "author": "class.lb_fm@tag.div.2@text##作者：",
      "coverUrl": "class.lb_fm@tag.img@src",
      "intro": "class.lb_jj@tag.div.3@text",
      "kind": "class.lb_fm@tag.div.3@text##类别：",
      "lastChapter": "class.lb_fm@tag.div.4@tag.a@text",
      "name": "class.lb_fm@tag.div.0@text",
      "tocUrl": "@js:\nif(baseUrl.indexOf(\"txt\")!=-1){\n\tbaseUrl=baseUrl.replace(\"txt\",\"\");\n}\nbaseUrl=baseUrl.replace(\"h.\",\"book.\");"
    },
    "ruleContent": {
      "content": "id.content@html",
      "nextContentUrl": "text.下一章.0@href##(.*_.*\\.html)##$1##"
    },
    "ruleExplore": {},
    "ruleSearch": {
      "author": "tag.a.1@text",
      "bookList": "class.line",
      "bookUrl": "tag.a.0@href",
      "name": "tag.a.0@text"
    },
    "ruleToc": {
      "chapterList": "@js:\nvar list=[];\nvar datatxt=result.match(/booklist clearfix([^@]*)<a href=\"https:\\/\\/book\\.189dg\\.com/)[1];\nvar strongList=datatxt.split(\"</strong>\");\nvar data=\"\";\nfor(var i=2,len=strongList.length;i<len;i++){\n\tdata=data.concat(strongList[i]);\n}\nvar datalist=data.split(\"<a href=\");\nif(datalist.length>1){\n\tfor(var i=1,len=datalist.length;i<len;i++){\n\t\tvar temp=datalist[i].match(/(.*\\.html)>(.*)<\\/a></);\n\t\tlist.push({\n\t\t\t\"chapterName\":temp[2],\n\t\t\t\"chapterUrl\":baseUrl+temp[1]\n\t\t});\n\t}\n}\nlist;",
      "chapterName": "chapterName",
      "chapterUrl": "chapterUrl",
      "nextTocUrl": ""
    },
    "searchUrl": "https://h.189dg.com/search.php?type=articlename&key={{key}},{\n\"charset\": \"gbk\"\n}",
    "weight": 0
  }]