[{"bookSourceComment": "", "bookSourceGroup": "我的书源,刘备书源", "bookSourceName": "🍑 吾爱耽美", "bookSourceType": 0, "bookSourceUrl": "http://m.52dmshu.com", "bookUrlPattern": "", "customOrder": 24367, "enabled": true, "enabledExplore": true, "exploreUrl": "总点击榜::/novel/allvisit.html\n月点击榜::/novel/monthvisit.html\n周点击榜::/novel/weekvisit.html\n总推荐榜::/novel/allvote.html\n月推荐榜::/novel/monthvote.html\n周推荐榜::/novel/weekvote.html\n总收藏榜::/novel/marknum.html\n总字数榜::/novel/fontsize.html\n评分人数::/novel/starnum.html\n打赏人数::/novel/rewardnum.html\n重生耽美::/chongsheng/{{page}}.html\n古代耽美::/guyan/{{page}}.html\n耽美宠文::/chongwen/{{page}}.html\n经典耽美::/qingchun/{{page}}.html\n虐心耽美::/niexin/{{page}}.html\n校园耽美::/xiaoyuan/{{page}}.html\n强强耽美::/qiangqiang/{{page}}.html\n言情总裁::/yanqing/{{page}}.html", "header": "", "lastUpdateTime": 1612409553319, "loginUrl": "", "ruleBookInfo": {"author": "[property=\"og:novel:author\"]@content", "coverUrl": "[property=\"og:image\"]@content", "init": "", "intro": "[property=\"og:description\"]@content", "kind": "[property=\"og:novel:category\"]@content&&[property=\"og:novel:status\"]@content&&[property=\"og:novel:update_time\"]@content##\\s.*", "lastChapter": "[property=\"og:novel:latest_chapter_name\"]@content", "name": "[property=\"og:novel:book_name\"]@content", "tocUrl": "id.btnList@tag.a.1@href", "wordCount": ""}, "ruleContent": {"content": "id.chaptercontent@tag.p@text", "imageStyle": "0", "nextContentUrl": "id.pb_next@tag.a@href", "sourceRegex": "", "webJs": ""}, "ruleExplore": {"author": "class.author@text##作者.", "bookList": "class.hot_sale||ul@li!0", "bookUrl": "tag.a@href", "coverUrl": "class.lazy@data-original", "intro": "class.review@text##简介.", "kind": "class.s1@text##\\[|\\]", "lastChapter": "", "name": "class.title@text||class.s2@text", "wordCount": ""}, "ruleSearch": {"author": "class.pt-author@text##作者.|\\|.*", "bookList": "class.ptm-card-content@tag.li", "bookUrl": "tag.a.1@href", "coverUrl": "tag.img@src", "intro": "class.pt-desc@text##简介.", "kind": "tag.span.0@text&&tag.a.2@text", "lastChapter": "tag.a.-1@text", "name": "tag.a.1@text", "wordCount": ""}, "ruleToc": {"chapterList": "id.chapterlist@tag.dd", "chapterName": "tag.a@text", "chapterUrl": "tag.a@href", "isVip": "", "nextTocUrl": "id.next@tag.a@href", "updateTime": ""}, "searchUrl": "/book.php?action=search&searchtype=novelname&searchkey={{key}}&input=&page={{page}},{\n  \"charset\": \"gbk\"\n}", "weight": 0, "BookSourceComment": ""}]