[  {
    "bookSourceComment": "",
    "bookSourceGroup": "我的书源",
    "bookSourceName": "笔趣",
    "bookSourceType": 0,
    "bookSourceUrl": "http://www.biquw.com",
    "bookUrlPattern": "",
    "customOrder": 800,
    "enabled": true,
    "enabledExplore": true,
    "exploreUrl": "默认::/xs/quanbu-default-0-0-0-0-0-0-{{page}}.html\n点击::/xs/quanbu-allvisit-0-0-0-0-0-0-{{page}}.html\n推荐::/xs/quanbu-allvote-0-0-0-0-0-0-{{page}}.html\n收藏::/xs/quanbu-goodnum-0-0-0-0-0-0-{{page}}.html\n字数::/xs/quanbu-size-0-0-0-0-0-0-{{page}}.html\n时间::/xs/quanbu-postdate-0-0-0-0-0-0-{{page}}.html\n玄幻::/xs/1-default-0-0-0-0-2-0-{{page}}.html\n仙侠::/xs/2-default-0-0-0-0-2-0-{{page}}.html\n都市::/xs/3-default-0-0-0-0-2-0-{{page}}.html\n军史::/xs/4-default-0-0-0-0-2-0-{{page}}.html\n网游::/xs/5-default-0-0-0-0-2-0-{{page}}.html\n科幻::/xs/6-default-0-0-0-0-2-0-{{page}}.html\n灵异::/xs/7-default-0-0-0-0-2-0-{{page}}.html\n言情::/xs/8-default-0-0-0-0-2-0-{{page}}.html\n其他::/xs/9-default-0-0-0-0-2-0-{{page}}.html",
    "lastUpdateTime": 1616237658778,
    "loginUrl": "",
    "ruleBookInfo": {
      "author": "[property=\"og:novel:author\"]@content",
      "coverUrl": "[property=\"og:image\"]@content",
      "intro": "class.bookinfo_intro@textNodes##您要是觉得《|》还不错.*",
      "kind": "[property=\"og:novel:category\"]@content&&[property=\"og:novel:status\"]@content&&[property=\"og:novel:update_time\"]@content##小说|\\s.*",
      "lastChapter": "[property=\"og:novel:latest_chapter_name\"]@content",
      "name": "[property=\"og:novel:book_name\"]@content"
    },
    "ruleContent": {
      "content": "id.htmlContent@textNodes"
    },
    "ruleExplore": {
      "author": "tag.span.1@text",
      "bookList": "class.sitebox@dl",
      "bookUrl": "tag.a.1@href",
      "coverUrl": "tag.img@src",
      "intro": "tag.dd.2@text",
      "kind": "tag.span.0@text##\\s.*",
      "lastChapter": "tag.a.2@text##正文.",
      "name": "tag.a.1@text"
    },
    "ruleSearch": {
      "author": "class.s3@text",
      "bookList": "ul@li",
      "bookUrl": "class.s1@tag.a@href",
      "coverUrl": "class.s1@tag.a@href@js:var o=result.match(/\\/book\\/(\\d+)/); if(o!=null){'/files/article/image/'+parseInt(o[1]/1000)+'/'+o[1]+'/'+o[1]+'s.jpg';}",
      "intro": "",
      "kind": "class.s5@text&&class.s6@text",
      "lastChapter": "class.s2@text##正文.",
      "name": "class.s1@text",
      "wordCount": "class.s4@text"
    },
    "ruleToc": {
      "chapterList": "class.book_list@tag.li",
      "chapterName": "tag.a@text##正文.",
      "chapterUrl": "tag.a@href"
    },
    "searchUrl": "/modules/article/search.php,{\n  \"method\": \"POST\",\n  \"body\": \"action=login&searchkey={{key}}\"\n}",
    "weight": 0
  }]