[  {
    "bookSourceComment": "error:failed to connect to cffote.com/47.89.37.117 (port 80) from /192.168.0.103 (port 37684) after 15000ms: isConnected failed: ETIMEDOUT (Connection timed out)\n",
    "bookSourceGroup": "我的书源",
    "bookSourceName": "📚 九九藏书[仅发现]",
    "bookSourceType": 0,
    "bookSourceUrl": "http://cffote.com",
    "bookUrlPattern": "",
    "customOrder": -24779,
    "enabled": true,
    "enabledExplore": true,
    "exploreUrl": "排行榜::/top/index.html\n传记回忆::/book/index8607.html?type=传记回忆&page={{page}}\n英文读本::/book/index3dfd.html?type=英文读本&page={{page}}\n杂文随笔::/book/indexf804.html?type=杂文随笔&page={{page}}\n现代小说::/book/index8233.html?type=现代小说&page={{page}}\n言情小说::/book/index2ede.html?type=言情小说&page={{page}}\n历史小说::/book/indexdf8b.html?type=历史小说&page={{page}}\n侦探推理::/book/index2fb0.html?type=侦探推理&page={{page}}\n惊悚悬疑::/book/indexb6c0.html?type=惊悚悬疑&page={{page}}\n网络玄幻::/book/index9caf.html?type=网络玄幻&page={{page}}\n寓言童话::/book/index405c.html?type=寓言童话&page={{page}}\n青春都市::/book/indexa688.html?type=青春都市&page={{page}}\n社会心理::/book/indexe749.html?type=社会心理&page={{page}}\n外国小说::/book/indexfa5f.html?type=外国小说&page={{page}}\n科幻小说::/book/index1519.html?type=科幻小说&page={{page}}\n当代小说::/book/index8385.html?type=当代小说&page={{page}}\n武侠小说::/book/index9ce1.html?type=武侠小说&page={{page}}\n纪实报告::/book/indexa758.html?type=纪实报告&page={{page}}\n世界历史::/book/indexdcf8.html?type=世界历史&page={{page}}\n中国历史::/book/index5516.html?type=中国历史&page={{page}}\n科普学习::/book/indexa3d4.html?type=科普学习&page={{page}}\n诗歌戏曲::/book/indexa309.html?type=诗歌戏曲&page={{page}}\n宗教哲学::/book/index9aa1.html?type=宗教哲学&page={{page}}\n文学理论::/book/indexb534.html?type=文学理论&page={{page}}\n日语读物::/book/index3fe0.html?type=日语读物\n作品集::/book/index0a67.html?type=作品集&page={{page}}\n国学/古籍::/book/index5cf6.html?type=国学%2F古籍&page={{page}}\n战争军事::/book/index3315.html?type=战争军事&page={{page}}\n政治经济::/book/index9624.html?type=政治经济&page={{page}}\n古典文学::/book/index143b.html?type=古典文学&page={{page}}\n官场小说::/book/index9233.html?type=官场小说&page={{page}}\n轻小说::/book/index52ad.html?type=轻小说&page={{page}}",
    "lastUpdateTime": 1602913982320,
    "loginUrl": "",
    "ruleBookInfo": {
      "author": "id.book_info@tag.h4.0@tag.a@text",
      "coverUrl": "id.book_info@tag.img@src",
      "intro": "class.intro@tag.p@text",
      "name": "id.book_info@tag.h2@text"
    },
    "ruleContent": {
      "content": "@css:#content > div@text"
    },
    "ruleExplore": {},
    "ruleSearch": {
      "author": "tag.h4.0@tag.a@text",
      "bookList": "class.list_box@tag.li",
      "bookUrl": "tag.h2@tag.a@href",
      "coverUrl": "tag.a@tag.img@src",
      "intro": "class.intro@text##^\\s+",
      "kind": "tag.h4.1@tag.a@text",
      "lastChapter": "@css:h4:contains(标签:) a@text##^|\\s+## \\#",
      "name": "tag.h2@tag.a@text"
    },
    "ruleToc": {
      "chapterList": "id.dir@tag.dd",
      "chapterName": "tag.a@text",
      "chapterUrl": "tag.a@href"
    },
    "searchUrl": "http://cffote.com/book/search.php?s=13139900387823019677&type=站内&q={{key}}",
    "weight": 0
  }]