[{"bookSourceComment": "", "bookSourceGroup": "我的书源", "bookSourceName": "🎉 精品小说网", "bookSourceType": 0, "bookSourceUrl": "https://jpxs123.com", "customOrder": -115561, "enabled": true, "enabledExplore": true, "exploreUrl": "", "lastUpdateTime": 1612586998651, "ruleBookInfo": {"author": "@css:.infos>span:eq(1)>a@text", "coverUrl": "@css:img@src", "intro": "@css:.infos>p@html", "name": "@css:.infos>h1@text"}, "ruleContent": {"content": "@css:.read_chapterDetail@textNodes"}, "ruleExplore": {}, "ruleSearch": {"author": "author", "bookList": "+<js>org.jsoup.Jsoup.parse(result).select(\".bk\").toArray().map(bk=>({name:bk.select(\"h3\").text(),author:String(bk.select(\".booknews\").html()).replace(/<label.*label>/g,\"\"),kind:\"\",intro:bk.select(\"p\").html(),last:bk.select(\".date\").text(),cover:bk.select(\"img\").attr(\"src\"),url:\"http://jpxs123.com\"+bk.select(\"h3>a\").attr(\"href\")}))</js>", "bookUrl": "url", "coverUrl": "cover", "intro": "intro", "kind": "kind", "lastChapter": "last", "name": "name"}, "ruleToc": {"chapterList": "+@css:.book_list.clearfix a", "chapterName": "text", "chapterUrl": "href"}, "searchUrl": "/e/search/index.php,{\n  \"charset\": \"gbk\",\n  \"method\": \"POST\",\n  \"body\": \"keyboard={{key}}&show=title&classid=0\"\n}", "weight": 0, "BookSourceComment": ""}]