[{"bookSourceComment": "", "bookSourceGroup": "我的书源", "bookSourceName": "🎉 万书楼", "bookSourceType": 0, "bookSourceUrl": "https://www.wshulou.com", "customOrder": -115194, "enabled": true, "enabledExplore": true, "exploreUrl": "玄幻奇幻::/xuanhuan/{{page}}.html\n都市人生::/dushi/{{page}}.html\n仙侠武侠::/xianxia/{{page}}.html\n军事历史::/junshi/{{page}}.html\n女频言情::/yanqing/{{page}}.html\n游戏竞技::/wangyou/{{page}}.html\n科幻恐怖::/kehuan/{{page}}.html\n综合其他::/qita/{{page}}.html\n完本小说::/wanben/{{page}}.html", "lastUpdateTime": 1612782934855, "ruleBookInfo": {"author": "class.booktag@tag.a.0@text", "coverUrl": "class.bookintro@tag.img.0@src", "init": "class.book pt10", "kind": "class.booktime@text&&class.booktag@tag.span.0@text&&class.booktag@tag.span.2@text##更新时间：", "lastChapter": "class.bookchapter@tag.a.0@text", "name": "class.booktitle@tag.h1@text", "tocUrl": "text.全部章节目录@href"}, "ruleContent": {"content": "class.readcontent@html", "nextContentUrl": "id.linkNext@href"}, "ruleExplore": {}, "ruleSearch": {"author": "class.author.0@text", "bookList": "class.bookbox", "bookUrl": "class.bookname@tag.a.0@href", "intro": "class.update@text##简介：", "kind": "class.author.1@text&&class.author.2@text##字数：", "lastChapter": "class.cat@tag.a.0@text", "name": "class.bookname@tag.a.0@text"}, "ruleToc": {"chapterList": "id.list-chapterAll@tag.dd", "chapterName": "tag.a@text", "chapterUrl": "tag.a@href"}, "searchUrl": "/modules/article/search.php?keyword={{key}},{\n  \"charset\": \"utf-8\"\n}", "weight": 0, "BookSourceComment": ""}]