[  {
    "bookSourceComment": "点击地址栏下载\n1230之后的版本可用",
    "bookSourceGroup": "我的书源",
    "bookSourceName": "📥 知轩藏书info",
    "bookSourceType": 0,
    "bookSourceUrl": "http://www.zxcs.info",
    "bookUrlPattern": "",
    "customOrder": -115901,
    "enabled": true,
    "enabledExplore": true,
    "exploreUrl": "都市::/sort/3/page/{{page}}\n历史::/sort/15/page/{{page}}\n军事::/sort/16/page/{{page}}\n武侠::/sort/6/page/{{page}}\n\n灵异::/sort/13/page/{{page}}\n仙侠::/sort/7/page/{{page}}\n奇幻::/sort/9/page/{{page}}\n玄幻::/sort/10/page/{{page}}\n\n科幻::/sort/12/page/{{page}}\n竞技::/sort/18/page/{{page}}\n游戏::/sort/19/page/{{page}}\n次元::/sort/20/page/{{page}}\n\n\n架空历史::/tag/架空历史/page/{{page}}\n清史民国::/tag/清史民国/page/{{page}}\n军事战争::/tag/军事战争/page/{{page}}\n\n官场沉浮::/tag/官场沉浮/page/{{page}}\n娱乐明星::/tag/娱乐明星/page/{{page}}\n\n都市生活::/tag/都市生活/page/{{page}}\n异术超能::/tag/异术超能/page/{{page}}\n\n灵异奇谈::/tag/灵异奇谈/page/{{page}}\n恐怖惊悚::/tag/恐怖惊悚/page/{{page}}\n悬疑探险::/tag/悬疑探险/page/{{page}}\n推理侦探::/tag/推理侦探/page/{{page}}\n\n传统武侠::/tag/传统武侠/page/{{page}}\n武侠幻想::/tag/武侠幻想/page/{{page}}\n同人小说::/tag/同人小说/page/{{page}}\n\n 新 入 库 ::/map.html",
    "header": "",
    "lastUpdateTime": 1610038973181,
    "loginUrl": "",
    "ruleBookInfo": {
      "author": "",
      "canReName": "true",
      "coverUrl": "id.content@tag.img@src",
      "init": "",
      "intro": "id.content@tag.p.2@textNodes##.*】(：|\\:)\\s*",
      "kind": "class.date@tag.a!0@text",
      "lastChapter": "",
      "name": "",
      "tocUrl": "class.down_2@tag.a@href",
      "wordCount": ""
    },
    "ruleContent": {
      "content": "",
      "nextContentUrl": "",
      "sourceRegex": "",
      "webJs": ""
    },
    "ruleExplore": {
      "author": "",
      "bookList": "",
      "bookUrl": "",
      "coverUrl": "",
      "intro": "",
      "kind": "",
      "lastChapter": "",
      "name": "",
      "wordCount": ""
    },
    "ruleSearch": {
      "author": "tag.a.0@text##.*作者：",
      "bookList": "id.plist||id.content@tag.li",
      "bookUrl": "tag.a.0@href",
      "coverUrl": "",
      "intro": "class.des@textNodes",
      "kind": "tag.a.1@text&&tag.a.2@html&&class.riqi@text##.*g\\/|\\\".*",
      "lastChapter": "{{'校对全本↬地址栏下载'}}📥",
      "name": "tag.a.0@text##《(.*)》##$1###",
      "wordCount": ""
    },
    "ruleToc": {
      "chapterList": "class.downfile.-1@tag.a",
      "chapterName": "{{book.latestChapterTitle}}",
      "chapterUrl": "href",
      "nextTocUrl": "",
      "updateTime": ""
    },
    "searchUrl": "/index.php?keyword={{key}}&page={{page}}",
    "weight": 0
  }]