[  {
    "bookSourceComment": "",
    "bookSourceGroup": "🎉精品",
    "bookSourceName": "🎉 书阅屋",
    "bookSourceType": 0,
    "bookSourceUrl": "https://www.biqugewx.com",
    "customOrder": -32612,
    "enabled": true,
    "enabledExplore": true,
    "lastUpdateTime": 1602570759085,
    "ruleBookInfo": {
      "author": "id.info@tag.p.0@text##作者：",
      "coverUrl": "id.fmimg@tag.img.0@src",
      "intro": "id.intro@tag.p.0@text",
      "name": "id.info@tag.h1.0@text"
    },
    "ruleContent": {
      "content": "id.content@textNodes",
      "replaceRegex": "##一秒记住(.|\\n)*免费阅读！|百度搜索(.|\\n)*免费阅读。"
    },
    "ruleExplore": {},
    "ruleSearch": {
      "author": "class.odd.1@text||id.info@tag.p.0@text##作者：",
      "bookList": "class.box_con white||class.grid@tag.tr!0",
      "bookUrl": "class.odd.0@tag.a.0@href",
      "coverUrl": "id.fmimg@tag.img.0@src",
      "kind": "class.con_top@text##.*网\\>|\\>.*",
      "lastChapter": "class.even.0@tag.a.0@text||id.info@tag.p.2@text",
      "name": "class.odd.0@tag.a.0@text||id.info@tag.h1.0@text"
    },
    "ruleToc": {
      "chapterList": "id.list@tag.dd",
      "chapterName": "tag.a@text",
      "chapterUrl": "tag.a@href"
    },
    "searchUrl": "https://www.biqugewx.com/modules/article/search.php?searchkey={{key}},{\n  \"charset\": \"gbk\"\n}",
    "weight": 0
  }]