[  {
    "bookSourceComment": "",
    "bookSourceName": "呦呦看书",
    "bookSourceType": 0,
    "bookSourceUrl": "https://www.youyoukanshu.com",
    "customOrder": 0,
    "enabled": true,
    "enabledExplore": true,
    "lastUpdateTime": 1613732285680,
    "ruleBookInfo": {
      "author": "##作者：([^<]+)<##$1###",
      "coverUrl": "class.bookcover@img@src",
      "intro": "class.intro@text",
      "kind": "##分类：([^<]+)<##$1###",
      "name": "h1@text"
    },
    "ruleContent": {
      "content": "class.content@html"
    },
    "ruleExplore": {},
    "ruleSearch": {
      "author": "tag.td.-2@text",
      "bookList": "table@tbody@tr",
      "bookUrl": "tag.a.0@href",
      "coverUrl": "",
      "lastChapter": "tag.a.1@text",
      "name": "tag.a.0@text"
    },
    "ruleToc": {
      "chapterList": "class.list-group@li@a",
      "chapterName": "text",
      "chapterUrl": "href"
    },
    "searchUrl": "https://www.youyoukanshu.com/search.php?search={{key}}",
    "weight": 0
  }]